wiktextract/__init__.py
wiktextract/categories.py
wiktextract/clean.py
wiktextract/config.py
wiktextract/datautils.py
wiktextract/english_words.py
wiktextract/form_descriptions.py
wiktextract/hieroglyphs.py
wiktextract/inflection.py
wiktextract/inflectiondata.py
wiktextract/linkages.py
wiktextract/page.py
wiktextract/parts_of_speech.py
wiktextract/places.py
wiktextract/pronunciations.py
wiktextract/tags.py
wiktextract/taxondata.py
wiktextract/thesaurus.py
wiktextract/topics.py
wiktextract/translations.py
wiktextract/unsupported_titles.py
wiktextract/wikihtml.py
wiktextract/wiktionary.py
wiktextract/zh_pron_tags.py
wiktextract-1.99.7.data/scripts/wiktwords
wiktextract-1.99.7.dist-info/LICENSE
wiktextract-1.99.7.dist-info/METADATA
wiktextract-1.99.7.dist-info/WHEEL
wiktextract-1.99.7.dist-info/top_level.txt
wiktextract-1.99.7.dist-info/RECORD
