Metadata-Version: 2.1
Name: wiktextract
Version: 1.99.7
Summary: Wiktionary dump file parser and multilingual data extractor
Home-page: https://ylonen.org
Author: Tatu Ylonen
Author-email: ylo@clausal.com
License: MIT
Download-URL: https://github.com/tatuylonen/wiktextract
Platform: UNKNOWN
Classifier: Development Status :: 3 - Alpha
Classifier: Intended Audience :: Developers
Classifier: Intended Audience :: Science/Research
Classifier: License :: OSI Approved :: MIT License
Classifier: Natural Language :: English
Classifier: Operating System :: OS Independent
Classifier: Operating System :: POSIX :: Linux
Classifier: Programming Language :: Python
Classifier: Programming Language :: Python :: 3.6
Classifier: Programming Language :: Python :: 3.7
Classifier: Programming Language :: Python :: 3.8
Classifier: Programming Language :: Python :: 3.9
Classifier: Programming Language :: Python :: 3 :: Only
Classifier: Topic :: Text Processing
Classifier: Topic :: Text Processing :: Linguistic
License-File: LICENSE
